fileprotector/__main__.py
fileprotector-0.1.2.dist-info/licenses/LICENSE
fileprotector-0.1.2.dist-info/METADATA
fileprotector-0.1.2.dist-info/WHEEL
fileprotector-0.1.2.dist-info/entry_points.txt
fileprotector-0.1.2.dist-info/top_level.txt
fileprotector-0.1.2.dist-info/RECORD
