Metadata-Version: 2.4
Name: fileprotector
Version: 0.1.2
Summary: Encrypt PDF and Excel files in bulk using a password
Author: Yali Achitov
Requires-Python: >=3.7
License-File: LICENSE
Requires-Dist: PyPDF2>=3.0.1
Requires-Dist: msoffcrypto-tool
Dynamic: license-file
